{
  "app_name": "cloudRestaurant",
  "app_mode": "debug",
  "app_host": "localhost",
  "app_port": "8090",

  "短信验证相关": "参数",
  "sms": {
    "sign_name": "go短信验证学习",
    "template_code": "SMS_274605316",
    "app_key": "LTAI5tBirWZEg7KmmWVy1nwk",
    "app_secret": "CKtUz5j4W0XtAkaj3REma5iMhw2qEE",
    "endpoint": "dysmsapi.aliyuncs.com"
  },
  "database": {
    "driver": "mysql",
    "user": "root",
    "password": "123456",
    "host": "127.0.0.1",
    "port": "3306",
    "db_name": "cloudrestaurant",
    "charset": "utf8mb4",
    "parseTime": "True",
    "loc": "Local"
  },
  "redis": {
    "host": "127.0.0.1",
    "port": "6379",
    "password": "",
    "db": 0
  }
}